django_markdown_editor_next/__init__.py
django_markdown_editor_next/fields.py
django_markdown_editor_next/views.py
django_markdown_editor_next/widgets.py
django_markdown_editor_next/static/django_markdown_editor_next/css/markdown_editor.css
django_markdown_editor_next/static/django_markdown_editor_next/js/markdown_editor.js
django_markdown_editor_next/templates/django_markdown_editor_next/widget.html
django_markdown_editor_next-0.5.dist-info/LICENSE
django_markdown_editor_next-0.5.dist-info/METADATA
django_markdown_editor_next-0.5.dist-info/WHEEL
django_markdown_editor_next-0.5.dist-info/top_level.txt
django_markdown_editor_next-0.5.dist-info/RECORD
