Metadata-Version: 2.1
Name: django-markdown-editor-next
Version: 0.5
Summary: A Django package to support Markdown text editor in Django admin
Home-page: https://github.com/aliahadmd/django-markdown-editor-next
Author: Ali
Author-email: ali@aliahad.com
License: MIT
Classifier: Environment :: Web Environment
Classifier: Framework :: Django
Classifier: Intended Audience :: Developers
Classifier: License :: OSI Approved :: MIT License
Classifier: Operating System :: OS Independent
Classifier: Programming Language :: Python
Classifier: Programming Language :: Python :: 3
Classifier: Programming Language :: Python :: 3.6
Classifier: Programming Language :: Python :: 3.7
Classifier: Programming Language :: Python :: 3.8
Classifier: Programming Language :: Python :: 3.9
Classifier: Programming Language :: Python :: 3.10
Classifier: Programming Language :: Python :: 3.11
Classifier: Programming Language :: Python :: 3.12
Classifier: Topic :: Internet :: WWW/HTTP
Classifier: Topic :: Internet :: WWW/HTTP :: Dynamic Content
License-File: LICENSE
Requires-Dist: Django >=2.2
Requires-Dist: markdown2 >=2.4.0
Requires-Dist: Pillow >=8.2.0
